winston/__init__.py
winston/cli.py
winston/stats.py
winston/utils.py
winston-0.2.3.dist-info/DESCRIPTION.rst
winston-0.2.3.dist-info/METADATA
winston-0.2.3.dist-info/RECORD
winston-0.2.3.dist-info/WHEEL
winston-0.2.3.dist-info/entry_points.txt
winston-0.2.3.dist-info/metadata.json
winston-0.2.3.dist-info/top_level.txt
