Metadata-Version: 2.0
Name: winston
Version: 0.2.3
Summary: A bit like PostGIS ST_SummaryStats for files on disk
Home-page: https://github.com/Maplecroft/Winston
Author: James Rutherford
Author-email: james.rutherford@maplecroft.com
License: MIT license
Keywords: winston
Platform: UNKNOWN
Classifier: Development Status :: 4 - Beta
Classifier: Intended Audience :: Developers
Classifier: License :: OSI Approved :: MIT License
Classifier: Natural Language :: English
Classifier: Programming Language :: Python :: 2
Classifier: Programming Language :: Python :: 2.7
Classifier: Programming Language :: Python :: 3
Classifier: Programming Language :: Python :: 3.3
Classifier: Programming Language :: Python :: 3.4
Classifier: Programming Language :: Python :: 3.5
Requires-Dist: click (==6.6)
Requires-Dist: numpy (==1.11.2)
Requires-Dist: rasterio (==0.36.0)
Requires-Dist: shapely (==1.5.17)
Requires-Dist: six (==1.10.0)
Requires-Dist: tablib (==0.11.2)
